k_util/__init__.py
k_util/core.py
k_util/logger.py
k_util/pather.py
k_util/region.py
k_util/serializable.py
k_util-0.2.0.dist-info/LICENSE
k_util-0.2.0.dist-info/METADATA
k_util-0.2.0.dist-info/WHEEL
k_util-0.2.0.dist-info/top_level.txt
k_util-0.2.0.dist-info/RECORD
