Metadata-Version: 2.1
Name: k-util
Version: 0.2.0
Summary: General utility scripts in Python 3.6.
Home-page: https://github.com/krinj/k-util
Author: Jakrin Juangbhanich
Author-email: juangbhanich.k@gmail.com
License: UNKNOWN
Platform: UNKNOWN
Classifier: Programming Language :: Python :: 3.6
